profiles/__init__.py
profiles/quora/__init__.py
profiles/quora/functions.py
profiles/quora/user.py
pyprofiles-0.0.2.dist-info/LICENSE
pyprofiles-0.0.2.dist-info/METADATA
pyprofiles-0.0.2.dist-info/WHEEL
pyprofiles-0.0.2.dist-info/top_level.txt
pyprofiles-0.0.2.dist-info/RECORD
